{"name":"Phoneme-classifier","tagline":"A Project for phoneme classification (for speech recognition systems) which includes 3 necessary components: a decoder (from HTK), a trainer and a database shuffler","body":"# phoneme-classifier \r\nA Project for phoneme classification (for speech recognition systems) which includes 3 necessary components: a decoder (from HTK), a trainer and a database shuffler\r\n# builds\r\nThe builds folder contains runnable executables\r\n","google":"","note":"Don't delete this file! It's used internally to help with page regeneration."}